sha256bit/__init__.py
sha256bit/cli.py
sha256bit-0.1.0.dist-info/METADATA
sha256bit-0.1.0.dist-info/WHEEL
sha256bit-0.1.0.dist-info/licenses/LICENSE
sha256bit-0.1.0.dist-info/RECORD
