Metadata-Version: 2.1
Name: sha256bit
Version: 0.1.0
Summary: SHA256 with bit granularity for message input length
Project-URL: Homepage, https://github.com/sebastien-riou/sha256bit
Project-URL: Bug Tracker, https://github.com/sebastien-riou/sha256bit/issues
Author: Sebastien Riou
License-File: LICENSE
Classifier: Development Status :: 4 - Beta
Classifier: License :: OSI Approved :: Apache Software License
Classifier: Operating System :: OS Independent
Classifier: Programming Language :: Python :: 3
Classifier: Programming Language :: Python :: 3.7
Classifier: Programming Language :: Python :: 3.8
Classifier: Programming Language :: Python :: 3.9
Classifier: Programming Language :: Python :: 3.10
Classifier: Programming Language :: Python :: 3.11
Classifier: Programming Language :: Python :: Implementation :: CPython
Classifier: Programming Language :: Python :: Implementation :: PyPy
Requires-Python: >=3.7
Requires-Dist: pysatl>=1.2.6
